{
  "cluster_id": 3,
  "name": "Zona Strada Florilor",
  "chunks": [
    {
      "chunk_id": 1,
      "api_response": {
        "code": "Ok",
        "distances": [
          [
            0,
            7.2,
            23.1,
            32.9,
            37.3,
            45.2,
            78.5,
            647,
            654.3,
            97.9,
            112.1,
            111.6,
            635.9,
            634.1,
            611.4,
            654,
            652.6,
            670,
            688.7,
            684.6,
            720,
            252.7,
            220.7,
            217.1
          ],
          [
            7.2,
            0,
            15.9,
            25.7,
            30,
            38,
            71.2,
            639.7,
            647.1,
            90.7,
            104.9,
            104.4,
            628.7,
            626.8,
            604.1,
            646.7,
            645.3,
            662.7,
            681.5,
            677.3,
            712.8,
            260,
            227.9,
            224.3
          ],
          [
            23.1,
            15.9,
            0,
            9.8,
            14.1,
            22.1,
            55.3,
            623.8,
            631.2,
            74.7,
            88.9,
            88.5,
            612.8,
            610.9,
            588.2,
            630.8,
            629.4,
            646.8,
            665.6,
            661.4,
            696.9,
            275.9,
            243.9,
            240.2
          ],
          [
            32.9,
            25.7,
            9.8,
            0,
            4.3,
            12.3,
            45.6,
            614,
            621.4,
            65,
            79.2,
            78.7,
            603,
            601.2,
            578.5,
            621,
            619.7,
            637,
            655.8,
            651.6,
            687.1,
            285.6,
            253.6,
            250
          ],
          [
            37.3,
            30,
            14.1,
            4.3,
            0,
            8,
            41.2,
            609.7,
            617.1,
            60.6,
            74.8,
            74.4,
            598.7,
            596.8,
            574.1,
            616.7,
            615.3,
            632.7,
            651.5,
            647.3,
            682.8,
            290,
            258,
            254.3
          ],
          [
            45.2,
            38,
            22.1,
            12.3,
            8,
            0,
            33.3,
            601.7,
            609.1,
            52.7,
            66.9,
            66.4,
            590.7,
            588.9,
            566.2,
            608.8,
            607.4,
            624.7,
            643.5,
            639.3,
            674.8,
            297.9,
            265.9,
            262.3
          ],
          [
            638.7,
            631.5,
            615.5,
            605.8,
            601.4,
            593.5,
            0,
            568.5,
            575.8,
            19.4,
            33.6,
            33.2,
            557.4,
            555.6,
            532.9,
            575.5,
            574.1,
            591.5,
            610.3,
            606.1,
            641.5,
            500.5,
            468.5,
            464.8
          ],
          [
            70.2,
            63,
            47,
            37.3,
            32.9,
            25,
            23,
            0,
            7.4,
            42.4,
            56.6,
            56.1,
            580.4,
            578.6,
            555.9,
            598.5,
            597.1,
            614.5,
            633.2,
            629.1,
            664.5,
            322.9,
            290.9,
            287.3
          ],
          [
            62.8,
            55.6,
            39.7,
            29.9,
            25.6,
            17.6,
            15.6,
            584.1,
            0,
            35.1,
            49.3,
            48.8,
            573.1,
            571.2,
            548.5,
            591.1,
            589.7,
            607.1,
            625.9,
            621.7,
            657.2,
            315.6,
            283.6,
            279.9
          ],
          [
            619.3,
            612,
            596.1,
            586.4,
            582,
            574.1,
            572.1,
            549.1,
            556.4,
            0,
            14.2,
            13.7,
            538,
            536.2,
            513.5,
            556.1,
            554.7,
            572.1,
            590.8,
            586.7,
            622.1,
            481.1,
            449,
            445.4
          ],
          [
            605.1,
            597.8,
            581.9,
            572.1,
            567.8,
            559.8,
            557.9,
            534.9,
            542.2,
            577.3,
            0,
            591,
            523.8,
            522,
            499.3,
            541.9,
            540.5,
            557.9,
            576.6,
            572.5,
            607.9,
            466.8,
            434.8,
            431.2
          ],
          [
            605.5,
            598.3,
            582.4,
            572.6,
            568.3,
            560.3,
            558.3,
            535.3,
            542.7,
            577.7,
            0.5,
            0,
            524.3,
            522.5,
            499.8,
            542.3,
            540.9,
            558.3,
            577.1,
            572.9,
            608.4,
            467.3,
            435.3,
            431.7
          ],
          [
            81.2,
            74,
            58.1,
            48.3,
            44,
            36,
            34,
            11,
            18.4,
            53.5,
            67.7,
            67.2,
            0,
            589.6,
            566.9,
            609.5,
            608.1,
            625.5,
            644.3,
            640.1,
            675.6,
            334,
            302,
            298.3
          ],
          [
            83.1,
            75.8,
            59.9,
            50.2,
            45.8,
            37.9,
            35.9,
            12.9,
            20.2,
            55.3,
            69.5,
            69,
            1.8,
            0,
            568.8,
            611.4,
            610,
            627.4,
            646.1,
            642,
            677.4,
            335.8,
            303.8,
            300.2
          ],
          [
            105.8,
            98.5,
            82.6,
            72.9,
            68.5,
            60.6,
            58.6,
            35.6,
            42.9,
            78,
            92.2,
            91.7,
            24.5,
            22.7,
            0,
            634.1,
            632.7,
            650.1,
            668.8,
            664.7,
            700.1,
            358.5,
            326.5,
            322.9
          ],
          [
            304.5,
            311.7,
            327.7,
            337.4,
            341.8,
            349.7,
            383,
            524.1,
            531.4,
            402.4,
            416.6,
            416.1,
            513,
            511.2,
            488.5,
            0,
            529.7,
            16,
            34.8,
            30.6,
            66,
            166.6,
            134.5,
            130.9
          ],
          [
            305.9,
            313.1,
            329.1,
            338.8,
            343.2,
            351.1,
            384.4,
            525.5,
            532.8,
            403.8,
            418,
            417.5,
            514.4,
            512.6,
            489.9,
            1.4,
            0,
            17.4,
            36.2,
            32,
            67.4,
            167.9,
            135.9,
            132.3
          ],
          [
            288.5,
            295.8,
            311.7,
            321.4,
            325.8,
            333.7,
            367,
            508.1,
            515.4,
            386.4,
            400.6,
            400.1,
            497,
            495.2,
            472.5,
            515.1,
            513.7,
            0,
            18.8,
            14.6,
            50.1,
            150.6,
            118.6,
            114.9
          ],
          [
            269.8,
            277,
            292.9,
            302.7,
            307,
            315,
            348.2,
            489.3,
            496.7,
            367.6,
            381.8,
            381.4,
            478.3,
            476.4,
            453.7,
            496.3,
            494.9,
            512.3,
            0,
            526.9,
            31.3,
            131.8,
            99.8,
            96.2
          ],
          [
            273.9,
            281.2,
            297.1,
            306.8,
            311.2,
            319.1,
            352.4,
            493.5,
            500.8,
            371.8,
            386,
            385.5,
            482.4,
            480.6,
            457.9,
            500.5,
            499.1,
            516.5,
            4.2,
            0,
            35.5,
            136,
            104,
            100.3
          ],
          [
            238.5,
            245.7,
            261.6,
            271.4,
            275.7,
            283.7,
            316.9,
            458,
            465.4,
            336.3,
            350.6,
            350.1,
            447,
            445.1,
            422.4,
            465,
            463.6,
            481,
            499.8,
            495.6,
            0,
            100.5,
            68.5,
            64.9
          ],
          [
            253.4,
            260.7,
            276.6,
            286.4,
            290.7,
            298.7,
            331.9,
            357.5,
            364.9,
            351.3,
            365.5,
            365.1,
            346.5,
            344.6,
            321.9,
            364.5,
            363.1,
            380.5,
            399.3,
            395.1,
            430.6,
            0,
            32.7,
            36.4
          ],
          [
            220.7,
            227.9,
            243.9,
            253.6,
            258,
            265.9,
            299.2,
            389.5,
            396.9,
            318.6,
            332.8,
            332.3,
            378.5,
            376.6,
            353.9,
            396.5,
            395.1,
            412.5,
            431.3,
            427.1,
            462.6,
            32,
            0,
            3.6
          ],
          [
            217.1,
            224.3,
            240.2,
            250,
            254.3,
            262.3,
            295.6,
            393.1,
            400.5,
            315,
            329.2,
            328.7,
            382.1,
            380.3,
            357.6,
            400.2,
            398.8,
            416.1,
            434.9,
            430.7,
            466.2,
            35.6,
            3.6,
            0
          ]
        ],
        "destinations": [
          {
            "distance": 16.499967835,
            "name": "Strada Crizantemelor",
            "location": [
              24.142388,
              45.809758
            ]
          },
          {
            "distance": 18.172865911,
            "name": "Strada Crizantemelor",
            "location": [
              24.142461,
              45.809795
            ]
          },
          {
            "distance": 13.742352467,
            "name": "Strada Crizantemelor",
            "location": [
              24.142626,
              45.809879
            ]
          },
          {
            "distance": 12.79319602,
            "name": "Strada Crizantemelor",
            "location": [
              24.142732,
              45.809932
            ]
          },
          {
            "distance": 10.30676435,
            "name": "Strada Crizantemelor",
            "location": [
              24.142775,
              45.809954
            ]
          },
          {
            "distance": 14.466117819,
            "name": "Strada Crizantemelor",
            "location": [
              24.142858,
              45.809996
            ]
          },
          {
            "distance": 7.260581531,
            "name": "Strada Lăcrămioarelor",
            "location": [
              24.142924,
              45.810205
            ]
          },
          {
            "distance": 17.073008956,
            "name": "Strada Lăcrămioarelor",
            "location": [
              24.143091,
              45.810034
            ]
          },
          {
            "distance": 17.896155673,
            "name": "Strada Lăcrămioarelor",
            "location": [
              24.14304,
              45.810088
            ]
          },
          {
            "distance": 10.763350458,
            "name": "Strada Lăcrămioarelor",
            "location": [
              24.142782,
              45.810347
            ]
          },
          {
            "distance": 13.501949515,
            "name": "Strada Lăcrămioarelor",
            "location": [
              24.142678,
              45.810452
            ]
          },
          {
            "distance": 9.362096235,
            "name": "Strada Lăcrămioarelor",
            "location": [
              24.142678,
              45.810452
            ]
          },
          {
            "distance": 5.605787147,
            "name": "Strada Lăcrămioarelor",
            "location": [
              24.143169,
              45.809952
            ]
          },
          {
            "distance": 14.143999543,
            "name": "Strada Lăcrămioarelor",
            "location": [
              24.143182,
              45.809939
            ]
          },
          {
            "distance": 13.31538182,
            "name": "Strada Lăcrămioarelor",
            "location": [
              24.143345,
              45.809768
            ]
          },
          {
            "distance": 12.012100205,
            "name": "Strada Pandurilor",
            "location": [
              24.142865,
              45.809234
            ]
          },
          {
            "distance": 10.831555788,
            "name": "Strada Pandurilor",
            "location": [
              24.142872,
              45.809238
            ]
          },
          {
            "distance": 16.684719878,
            "name": "Strada Pandurilor",
            "location": [
              24.142704,
              45.809141
            ]
          },
          {
            "distance": 16.819819241,
            "name": "Strada Pandurilor",
            "location": [
              24.14252,
              45.809034
            ]
          },
          {
            "distance": 14.238281685,
            "name": "Strada Pandurilor",
            "location": [
              24.14256,
              45.809057
            ]
          },
          {
            "distance": 1.991795267,
            "name": "Strada Pandurilor",
            "location": [
              24.142207,
              45.808852
            ]
          },
          {
            "distance": 17.324460158,
            "name": "Strada Țiglari",
            "location": [
              24.142234,
              45.808197
            ]
          },
          {
            "distance": 5.100403614,
            "name": "Strada Țiglari",
            "location": [
              24.141978,
              45.808433
            ]
          },
          {
            "distance": 12.880458851,
            "name": "Strada Țiglari",
            "location": [
              24.141946,
              45.808461
            ]
          }
        ],
        "durations": [
          [
            0,
            2,
            6.4,
            9.1,
            10.3,
            12.5,
            25.9,
            123.3,
            124.5,
            30,
            33,
            32.9,
            121.5,
            121.2,
            117.5,
            125,
            124.8,
            127.3,
            130,
            129.4,
            134.5,
            50.4,
            47.5,
            47.2
          ],
          [
            2,
            0,
            4.4,
            7.1,
            8.3,
            10.5,
            23.9,
            121.3,
            122.5,
            28,
            31,
            30.9,
            119.5,
            119.2,
            115.5,
            123,
            122.8,
            125.3,
            128,
            127.4,
            132.5,
            52.4,
            49.5,
            49.2
          ],
          [
            6.4,
            4.4,
            0,
            2.7,
            3.9,
            6.1,
            19.5,
            116.9,
            118.1,
            23.6,
            26.6,
            26.5,
            115.1,
            114.8,
            111.1,
            118.6,
            118.4,
            120.9,
            123.6,
            123,
            128.1,
            56.8,
            53.9,
            53.6
          ],
          [
            9.1,
            7.1,
            2.7,
            0,
            1.2,
            3.4,
            16.8,
            114.2,
            115.4,
            20.9,
            23.9,
            23.8,
            112.4,
            112.1,
            108.4,
            115.9,
            115.7,
            118.2,
            120.9,
            120.3,
            125.4,
            59.5,
            56.6,
            56.3
          ],
          [
            10.3,
            8.3,
            3.9,
            1.2,
            0,
            2.2,
            15.6,
            113,
            114.2,
            19.7,
            22.7,
            22.6,
            111.2,
            110.9,
            107.2,
            114.7,
            114.5,
            117,
            119.7,
            119.1,
            124.2,
            60.7,
            57.8,
            57.5
          ],
          [
            12.5,
            10.5,
            6.1,
            3.4,
            2.2,
            0,
            13.4,
            110.8,
            112,
            17.5,
            20.5,
            20.4,
            109,
            108.7,
            105,
            112.5,
            112.3,
            114.8,
            117.5,
            116.9,
            122,
            62.9,
            60,
            59.7
          ],
          [
            121.6,
            119.6,
            115.2,
            112.5,
            111.3,
            109.1,
            0,
            97.4,
            98.6,
            4.1,
            7.1,
            7,
            95.6,
            95.3,
            91.6,
            99.1,
            98.9,
            101.4,
            104.1,
            103.5,
            108.6,
            83.1,
            80.2,
            79.9
          ],
          [
            24.2,
            22.2,
            17.8,
            15.1,
            13.9,
            11.7,
            4.5,
            0,
            1.2,
            8.6,
            11.6,
            11.5,
            100.1,
            99.8,
            96.1,
            103.6,
            103.4,
            105.9,
            108.6,
            108,
            113.1,
            74.6,
            71.7,
            71.4
          ],
          [
            23,
            21,
            16.6,
            13.9,
            12.7,
            10.5,
            3.3,
            100.7,
            0,
            7.4,
            10.4,
            10.3,
            98.9,
            98.6,
            94.9,
            102.4,
            102.2,
            104.7,
            107.4,
            106.8,
            111.9,
            73.4,
            70.5,
            70.2
          ],
          [
            117.5,
            115.5,
            111.1,
            108.4,
            107.2,
            105,
            97.8,
            93.3,
            94.5,
            0,
            3,
            2.9,
            91.5,
            91.2,
            87.5,
            95,
            94.8,
            97.3,
            100,
            99.4,
            104.5,
            79,
            76.1,
            75.8
          ],
          [
            114.5,
            112.5,
            108.1,
            105.4,
            104.2,
            102,
            94.8,
            90.3,
            91.5,
            98.9,
            0,
            101.8,
            88.5,
            88.2,
            84.5,
            92,
            91.8,
            94.3,
            97,
            96.4,
            101.5,
            76,
            73.1,
            72.8
          ],
          [
            114.6,
            112.6,
            108.2,
            105.5,
            104.3,
            102.1,
            94.9,
            90.4,
            91.6,
            99,
            0.1,
            0,
            88.6,
            88.3,
            84.6,
            92.1,
            91.9,
            94.4,
            97.1,
            96.5,
            101.6,
            76.1,
            73.2,
            72.9
          ],
          [
            26,
            24,
            19.6,
            16.9,
            15.7,
            13.5,
            6.3,
            1.8,
            3,
            10.4,
            13.4,
            13.3,
            0,
            101.6,
            97.9,
            105.4,
            105.2,
            107.7,
            110.4,
            109.8,
            114.9,
            76.4,
            73.5,
            73.2
          ],
          [
            26.3,
            24.3,
            19.9,
            17.2,
            16,
            13.8,
            6.6,
            2.1,
            3.3,
            10.7,
            13.7,
            13.6,
            0.3,
            0,
            98.2,
            105.7,
            105.5,
            108,
            110.7,
            110.1,
            115.2,
            76.7,
            73.8,
            73.5
          ],
          [
            30,
            28,
            23.6,
            20.9,
            19.7,
            17.5,
            10.3,
            5.8,
            7,
            14.4,
            17.4,
            17.3,
            4,
            3.7,
            0,
            109.4,
            109.2,
            111.7,
            114.4,
            113.8,
            118.9,
            80.4,
            77.5,
            77.2
          ],
          [
            62.6,
            64.6,
            69,
            71.7,
            72.9,
            75.1,
            88.5,
            81.4,
            82.6,
            92.6,
            95.6,
            95.5,
            79.6,
            79.3,
            75.6,
            0,
            82.9,
            2.3,
            5,
            4.4,
            9.5,
            25.8,
            22.9,
            22.6
          ],
          [
            62.8,
            64.8,
            69.2,
            71.9,
            73.1,
            75.3,
            88.7,
            81.6,
            82.8,
            92.8,
            95.8,
            95.7,
            79.8,
            79.5,
            75.8,
            0.2,
            0,
            2.5,
            5.2,
            4.6,
            9.7,
            26,
            23.1,
            22.8
          ],
          [
            60.3,
            62.3,
            66.7,
            69.4,
            70.6,
            72.8,
            86.2,
            79.1,
            80.3,
            90.3,
            93.3,
            93.2,
            77.3,
            77,
            73.3,
            80.8,
            80.6,
            0,
            2.7,
            2.1,
            7.2,
            23.5,
            20.6,
            20.3
          ],
          [
            57.6,
            59.6,
            64,
            66.7,
            67.9,
            70.1,
            83.5,
            76.4,
            77.6,
            87.6,
            90.6,
            90.5,
            74.6,
            74.3,
            70.6,
            78.1,
            77.9,
            80.4,
            0,
            82.5,
            4.5,
            20.8,
            17.9,
            17.6
          ],
          [
            58.2,
            60.2,
            64.6,
            67.3,
            68.5,
            70.7,
            84.1,
            77,
            78.2,
            88.2,
            91.2,
            91.1,
            75.2,
            74.9,
            71.2,
            78.7,
            78.5,
            81,
            0.6,
            0,
            5.1,
            21.4,
            18.5,
            18.2
          ],
          [
            53.1,
            55.1,
            59.5,
            62.2,
            63.4,
            65.6,
            79,
            71.9,
            73.1,
            83.1,
            86.1,
            86,
            70.1,
            69.8,
            66.1,
            73.6,
            73.4,
            75.9,
            78.6,
            78,
            0,
            16.3,
            13.4,
            13.1
          ],
          [
            49.7,
            51.7,
            56.1,
            58.8,
            60,
            62.2,
            75.6,
            55.6,
            56.8,
            79.7,
            82.7,
            82.6,
            53.8,
            53.5,
            49.8,
            57.3,
            57.1,
            59.6,
            62.3,
            61.7,
            66.8,
            0,
            2.7,
            3
          ],
          [
            47,
            49,
            53.4,
            56.1,
            57.3,
            59.5,
            72.9,
            58.5,
            59.7,
            77,
            80,
            79.9,
            56.7,
            56.4,
            52.7,
            60.2,
            60,
            62.5,
            65.2,
            64.6,
            69.7,
            2.9,
            0,
            0.3
          ],
          [
            46.7,
            48.7,
            53.1,
            55.8,
            57,
            59.2,
            72.6,
            58.8,
            60,
            76.7,
            79.7,
            79.6,
            57,
            56.7,
            53,
            60.5,
            60.3,
            62.8,
            65.5,
            64.9,
            70,
            3.2,
            0.3,
            0
          ]
        ],
        "sources": [
          {
            "distance": 16.499967835,
            "name": "Strada Crizantemelor",
            "location": [
              24.142388,
              45.809758
            ]
          },
          {
            "distance": 18.172865911,
            "name": "Strada Crizantemelor",
            "location": [
              24.142461,
              45.809795
            ]
          },
          {
            "distance": 13.742352467,
            "name": "Strada Crizantemelor",
            "location": [
              24.142626,
              45.809879
            ]
          },
          {
            "distance": 12.79319602,
            "name": "Strada Crizantemelor",
            "location": [
              24.142732,
              45.809932
            ]
          },
          {
            "distance": 10.30676435,
            "name": "Strada Crizantemelor",
            "location": [
              24.142775,
              45.809954
            ]
          },
          {
            "distance": 14.466117819,
            "name": "Strada Crizantemelor",
            "location": [
              24.142858,
              45.809996
            ]
          },
          {
            "distance": 7.260581531,
            "name": "Strada Lăcrămioarelor",
            "location": [
              24.142924,
              45.810205
            ]
          },
          {
            "distance": 17.073008956,
            "name": "Strada Lăcrămioarelor",
            "location": [
              24.143091,
              45.810034
            ]
          },
          {
            "distance": 17.896155673,
            "name": "Strada Lăcrămioarelor",
            "location": [
              24.14304,
              45.810088
            ]
          },
          {
            "distance": 10.763350458,
            "name": "Strada Lăcrămioarelor",
            "location": [
              24.142782,
              45.810347
            ]
          },
          {
            "distance": 13.501949515,
            "name": "Strada Lăcrămioarelor",
            "location": [
              24.142678,
              45.810452
            ]
          },
          {
            "distance": 9.362096235,
            "name": "Strada Lăcrămioarelor",
            "location": [
              24.142678,
              45.810452
            ]
          },
          {
            "distance": 5.605787147,
            "name": "Strada Lăcrămioarelor",
            "location": [
              24.143169,
              45.809952
            ]
          },
          {
            "distance": 14.143999543,
            "name": "Strada Lăcrămioarelor",
            "location": [
              24.143182,
              45.809939
            ]
          },
          {
            "distance": 13.31538182,
            "name": "Strada Lăcrămioarelor",
            "location": [
              24.143345,
              45.809768
            ]
          },
          {
            "distance": 12.012100205,
            "name": "Strada Pandurilor",
            "location": [
              24.142865,
              45.809234
            ]
          },
          {
            "distance": 10.831555788,
            "name": "Strada Pandurilor",
            "location": [
              24.142872,
              45.809238
            ]
          },
          {
            "distance": 16.684719878,
            "name": "Strada Pandurilor",
            "location": [
              24.142704,
              45.809141
            ]
          },
          {
            "distance": 16.819819241,
            "name": "Strada Pandurilor",
            "location": [
              24.14252,
              45.809034
            ]
          },
          {
            "distance": 14.238281685,
            "name": "Strada Pandurilor",
            "location": [
              24.14256,
              45.809057
            ]
          },
          {
            "distance": 1.991795267,
            "name": "Strada Pandurilor",
            "location": [
              24.142207,
              45.808852
            ]
          },
          {
            "distance": 17.324460158,
            "name": "Strada Țiglari",
            "location": [
              24.142234,
              45.808197
            ]
          },
          {
            "distance": 5.100403614,
            "name": "Strada Țiglari",
            "location": [
              24.141978,
              45.808433
            ]
          },
          {
            "distance": 12.880458851,
            "name": "Strada Țiglari",
            "location": [
              24.141946,
              45.808461
            ]
          }
        ]
      },
      "point_ids": [
        "1D51A2FD",
        "CCF9DDB2",
        "5579BC0E",
        "B7A9FB55",
        "5D9A1D84",
        "40869FDD",
        "5B32CDB3",
        "2072CD84",
        "8A76E63A",
        "E4CEE2D8",
        "F5F12F76",
        "5D4BEA20",
        "314FA3EE",
        "1337C778",
        "B6D6F77E",
        "A570F645",
        "F97B06EE",
        "231F0CB8",
        "45F809F3",
        "A8D33C4C",
        "6891030F",
        "01AAAF58",
        "7EFD1863",
        "434243D0"
      ],
      "addresses": [
        "Strada Crizantemelor 13, Sibiu, Romania",
        "Strada Crizantemelor 12, Sibiu, Romania",
        "Strada Crizantemelor 16, Sibiu, Romania",
        "Strada Crizantemelor 17, Sibiu, Romania",
        "Strada Crizantemelor 18, Sibiu, Romania",
        "Strada Crizantemelor 19, Sibiu, Romania",
        "Strada Crizantemelor 21, Sibiu, Romania",
        "Strada Lăcrămioarelor 8, Sibiu, Romania",
        "Strada Lăcrămioarelor 10, Sibiu, Romania",
        "Strada Lăcrămioarelor 14, Sibiu, Romania",
        "Strada Lăcrămioarelor 16, Sibiu, Romania",
        "Strada Lăcrămioarelor 1, Sibiu, Romania",
        "Strada Lăcrămioarelor 6, Sibiu, Romania",
        "Strada Lăcrămioarelor 4, Sibiu, Romania",
        "Strada Lăcrămioarelor 2, Sibiu, Romania",
        "Strada Pandurilor 14, Sibiu, Romania",
        "Strada Pandurilor 13, Sibiu, Romania",
        "Strada Pandurilor 12, Sibiu, Romania",
        "Strada Pandurilor 7, Sibiu, Romania",
        "Strada Pandurilor 10, Sibiu, Romania",
        "Strada Pandurilor 1, Sibiu, Romania",
        "Strada Țiglarilor 34, Sibiu, Romania",
        "Strada Țiglarilor 45, Sibiu, Romania",
        "Strada Țiglarilor 40, Sibiu, Romania"
      ],
      "original_indices": [
        0,
        1,
        2,
        3,
        5,
        6,
        7,
        8,
        9,
        10,
        11,
        13,
        14,
        15,
        16,
        17,
        18,
        19,
        20,
        21,
        22,
        23,
        24,
        25
      ]
    }
  ]
}